biosimulators_libsbmlsim/__init__.py
biosimulators_libsbmlsim/__main__.py
biosimulators_libsbmlsim/_version.py
biosimulators_libsbmlsim/core.py
biosimulators_libsbmlsim/data_model.py
biosimulators_libsbmlsim-0.0.6.dist-info/METADATA
biosimulators_libsbmlsim-0.0.6.dist-info/WHEEL
biosimulators_libsbmlsim-0.0.6.dist-info/entry_points.txt
biosimulators_libsbmlsim-0.0.6.dist-info/top_level.txt
biosimulators_libsbmlsim-0.0.6.dist-info/RECORD
