Metadata-Version: 2.1
Name: biosimulators-libsbmlsim
Version: 0.0.6
Summary: BioSimulators-compliant command-line interface to LibSBMLsim <http://fun.bio.keio.ac.jp/software/libsbmlsim/>.
Home-page: http://fun.bio.keio.ac.jp/software/libsbmlsim/
Author: LibSBMLsim Team
Author-email: info@fun.bio.keio.ac.jp
License: MIT
Download-URL: http://fun.bio.keio.ac.jp/software/libsbmlsim/
Keywords: BioSimulators,systems biology,computational biology,mathematical model,kinetic model,simulation,SBML,SED-ML,COMBINE,OMEX
Platform: UNKNOWN
Classifier: Development Status :: 3 - Alpha
Classifier: Intended Audience :: Science/Research
Classifier: License :: OSI Approved :: MIT License
Classifier: Topic :: Scientific/Engineering :: Bio-Informatics
Requires-Dist: biosimulators-utils[logging,sbml] (>=0.1.118)
Requires-Dist: kisao
Requires-Dist: lxml
Requires-Dist: pandas
Provides-Extra: all
Requires-Dist: numpy ; extra == 'all'
Requires-Dist: python-dateutil ; extra == 'all'
Provides-Extra: docs
Provides-Extra: tests
Requires-Dist: numpy ; extra == 'tests'
Requires-Dist: python-dateutil ; extra == 'tests'
